{
  "accounts": [
    {
      "name": 40817810200000055320,
      "currency": "RUB",
      "balance": 1000000.0,
      "created_at": "2019-08-01",
      "transactions": [
        {
          "date": "2020-08-23",
          "processingDate": "2020-08-23",
          "description": "Оплата услуг МегаФон Урал, Номер телефона: 79111111111, 23.08.2020 11:59:59, Сумма 50.00 RUB, Банк-он-ЛайнСтатусУспешно Тип операцииОплата услугСумма операции50.00 ₽Проведено50.00 ₽Комиссия0.00 ₽Дата обработки23.08.2020Информация о терминалеBank-on-line, Россия, Ekaterinburg, ul. Chapaeva 3aОписаниеОплата услуг МегаФон Урал, Номер телефона: 79111111111, 23.08.2020 11:59:59, Сумма 50.00 RUB, Банк-он-ЛайнНомер телефона9111111111",
          "amount": 50.0,
          "commission": 0.0
        },
        {
          "date": "2020-08-23",
          "processingDate": "2020-08-23",
          "description": "Выдача наличных, 23.08.2020 11:59:59, Карта: 437562*4576, Сумма 1000.00 RUB, Россия, Банкомат: 66000002, Екатеринбург, Чапаева 3а, Код авторизации: 720013.СтатусУспешно Тип операцииВыдача наличныхСумма операции1 000.00 ₽Проведено1 000.00 ₽Комиссия0.00 ₽Дата обработки23.08.2020Информация о терминалеATM, Россия, Ekaterinburg, ul. Chapaeva 3aОписаниеВыдача наличных, 23.08.2020 11:59:59, Карта: 437562*4576, Сумма 1000.00 RUB, Россия, Банкомат: 66000002, Екатеринбург, Чапаева 3а, Код авторизации: 720013.",
          "amount": 1000.0,
          "commission": 0.0
        },
        {
          "date": "2020-08-23",
          "processingDate": "2020-08-23",
          "description": "Оплата товара/услуги, 23.08.2020 11:59:59, Карта: 437562*4576, Сумма 99.29 RUB, Великобритания, Терминал: WWW.ALIEXPRESS.COM, INTERNET , MCC 5964, Код авторизации: 418395СтатусУспешно Тип операцииОплата товаров/услугСумма операции99.29 ₽Зарезервировано99.29 ₽Проведено99.29 ₽Комиссия0.00 ₽Код подтверждения418395Время совершения операции23.08.2020 11:59:59Дата обработки23.08.2020Информация о терминалеeCommerce, Великобритания, INTERNET, ОписаниеОплата товара/услуги, 23.08.2020 11:59:59, Карта: 437562*4576, Сумма 99.29 RUB, Великобритания, Терминал: WWW.ALIEXPRESS.COM, INTERNET , MCC 5964, Код авторизации: 418395",
          "amount": 99.29,
          "commission": 0.0
        },
        {
          "date": "2020-08-23",
          "processingDate": "2020-08-23",
          "description": "Перевод просто так, 23.08.2020 11:59:59, Сумма 200.00 RUB, Банк-он-ЛайнСтатусУспешно Тип операцииПеревод по заявлению клиентаСумма операции200.00 ₽Проведено200.00 ₽Комиссия0.00 ₽Дата обработки23.08.2020Информация о терминалеBank-on-line, Россия, Ekaterinburg, ul. Chapaeva 3aОписаниеПеревод просто так, 23.08.2020 11:59:59, Сумма 200.00 RUB, Банк-он-Лайн",
          "amount": 200.0,
          "commission": 0.0
        },
        {
          "date": "2020-08-23",
          "processingDate": "2020-08-23",
          "description": "Покупка/продажа иностранной валюты от 23/08/2020. Без НДС, 23.08.2020 11:59:59, Сумма 100.08 RUB, Банк-он-ЛайнСтатусУспешно Тип операцииПеревод по заявлению клиентаСумма операции100.08 ₽Проведено100.08 ₽Комиссия0.00 ₽Дата обработки23.08.2020Информация о терминалеBank-on-line, Россия, Ekaterinburg, ul. Chapaeva 3aОписаниеПокупка/продажа иностранной валюты от 23/08/2020. Без НДС, 23.08.2020 11:59:59, Сумма 100.08 RUB, Банк-он-Лайн",
          "amount": 100.08,
          "commission": 0.0
        }
      ]
    },
    {
      "name": 40817840400000055321,
      "currency": "USD",
      "balance": 100000.0,
      "created_at": "2019-08-01",
      "transactions": [
        {
          "date": "2020-08-23",
          "processingDate": "2020-08-23",
          "description": "Оплата услуг МегаФон Урал, Номер телефона: 79111111111, 23.08.2020 11:59:59, Сумма 50.00 RUB, Банк-он-ЛайнСтатусУспешно Тип операцииОплата услугСумма операции50.00 ₽Проведено50.00 ₽Комиссия0.00 ₽Дата обработки23.08.2020Информация о терминалеBank-on-line, Россия, Ekaterinburg, ul. Chapaeva 3aОписаниеОплата услуг МегаФон Урал, Номер телефона: 79111111111, 23.08.2020 11:59:59, Сумма 50.00 RUB, Банк-он-ЛайнНомер телефона9111111111",
          "amount": 50.0,
          "commission": 0.0
        },
        {
          "date": "2020-08-23",
          "processingDate": "2020-08-23",
          "description": "Выдача наличных, 23.08.2020 11:59:59, Карта: 437562*4576, Сумма 1000.00 RUB, Россия, Банкомат: 66000002, Екатеринбург, Чапаева 3а, Код авторизации: 720013.СтатусУспешно Тип операцииВыдача наличныхСумма операции1 000.00 ₽Проведено1 000.00 ₽Комиссия0.00 ₽Дата обработки23.08.2020Информация о терминалеATM, Россия, Ekaterinburg, ul. Chapaeva 3aОписаниеВыдача наличных, 23.08.2020 11:59:59, Карта: 437562*4576, Сумма 1000.00 RUB, Россия, Банкомат: 66000002, Екатеринбург, Чапаева 3а, Код авторизации: 720013.",
          "amount": 1000.0,
          "commission": 0.0
        },
        {
          "date": "2020-08-23",
          "processingDate": "2020-08-23",
          "description": "Оплата товара/услуги, 23.08.2020 11:59:59, Карта: 437562*4576, Сумма 99.29 RUB, Великобритания, Терминал: WWW.ALIEXPRESS.COM, INTERNET , MCC 5964, Код авторизации: 418395СтатусУспешно Тип операцииОплата товаров/услугСумма операции99.29 ₽Зарезервировано99.29 ₽Проведено99.29 ₽Комиссия0.00 ₽Код подтверждения418395Время совершения операции23.08.2020 11:59:59Дата обработки23.08.2020Информация о терминалеeCommerce, Великобритания, INTERNET, ОписаниеОплата товара/услуги, 23.08.2020 11:59:59, Карта: 437562*4576, Сумма 99.29 RUB, Великобритания, Терминал: WWW.ALIEXPRESS.COM, INTERNET , MCC 5964, Код авторизации: 418395",
          "amount": 99.29,
          "commission": 0.0
        },
        {
          "date": "2020-08-23",
          "processingDate": "2020-08-23",
          "description": "Перевод просто так, 23.08.2020 11:59:59, Сумма 200.00 RUB, Банк-он-ЛайнСтатусУспешно Тип операцииПеревод по заявлению клиентаСумма операции200.00 ₽Проведено200.00 ₽Комиссия0.00 ₽Дата обработки23.08.2020Информация о терминалеBank-on-line, Россия, Ekaterinburg, ul. Chapaeva 3aОписаниеПеревод просто так, 23.08.2020 11:59:59, Сумма 200.00 RUB, Банк-он-Лайн",
          "amount": 200.0,
          "commission": 0.0
        },
        {
          "date": "2020-08-23",
          "processingDate": "2020-08-23",
          "description": "Покупка/продажа иностранной валюты от 23/08/2020. Без НДС, 23.08.2020 11:59:59, Сумма 100.08 RUB, Банк-он-ЛайнСтатусУспешно Тип операцииПеревод по заявлению клиентаСумма операции100.08 ₽Проведено100.08 ₽Комиссия0.00 ₽Дата обработки23.08.2020Информация о терминалеBank-on-line, Россия, Ekaterinburg, ul. Chapaeva 3aОписаниеПокупка/продажа иностранной валюты от 23/08/2020. Без НДС, 23.08.2020 11:59:59, Сумма 100.08 RUB, Банк-он-Лайн",
          "amount": 100.08,
          "commission": 0.0
        }
      ]
    },
    {
      "name": 40817978300000055322,
      "currency": "EUR",
      "balance": 100000.0,
      "created_at": "2019-08-01",
      "transactions": [
        {
          "date": "2020-08-23",
          "processingDate": "2020-08-23",
          "description": "Оплата услуг МегаФон Урал, Номер телефона: 79111111111, 23.08.2020 11:59:59, Сумма 50.00 RUB, Банк-он-ЛайнСтатусУспешно Тип операцииОплата услугСумма операции50.00 ₽Проведено50.00 ₽Комиссия0.00 ₽Дата обработки23.08.2020Информация о терминалеBank-on-line, Россия, Ekaterinburg, ul. Chapaeva 3aОписаниеОплата услуг МегаФон Урал, Номер телефона: 79111111111, 23.08.2020 11:59:59, Сумма 50.00 RUB, Банк-он-ЛайнНомер телефона9111111111",
          "amount": 50.0,
          "commission": 0.0
        },
        {
          "date": "2020-08-23",
          "processingDate": "2020-08-23",
          "description": "Выдача наличных, 23.08.2020 11:59:59, Карта: 437562*4576, Сумма 1000.00 RUB, Россия, Банкомат: 66000002, Екатеринбург, Чапаева 3а, Код авторизации: 720013.СтатусУспешно Тип операцииВыдача наличныхСумма операции1 000.00 ₽Проведено1 000.00 ₽Комиссия0.00 ₽Дата обработки23.08.2020Информация о терминалеATM, Россия, Ekaterinburg, ul. Chapaeva 3aОписаниеВыдача наличных, 23.08.2020 11:59:59, Карта: 437562*4576, Сумма 1000.00 RUB, Россия, Банкомат: 66000002, Екатеринбург, Чапаева 3а, Код авторизации: 720013.",
          "amount": 1000.0,
          "commission": 0.0
        },
        {
          "date": "2020-08-23",
          "processingDate": "2020-08-23",
          "description": "Оплата товара/услуги, 23.08.2020 11:59:59, Карта: 437562*4576, Сумма 99.29 RUB, Великобритания, Терминал: WWW.ALIEXPRESS.COM, INTERNET , MCC 5964, Код авторизации: 418395СтатусУспешно Тип операцииОплата товаров/услугСумма операции99.29 ₽Зарезервировано99.29 ₽Проведено99.29 ₽Комиссия0.00 ₽Код подтверждения418395Время совершения операции23.08.2020 11:59:59Дата обработки23.08.2020Информация о терминалеeCommerce, Великобритания, INTERNET, ОписаниеОплата товара/услуги, 23.08.2020 11:59:59, Карта: 437562*4576, Сумма 99.29 RUB, Великобритания, Терминал: WWW.ALIEXPRESS.COM, INTERNET , MCC 5964, Код авторизации: 418395",
          "amount": 99.29,
          "commission": 0.0
        },
        {
          "date": "2020-08-23",
          "processingDate": "2020-08-23",
          "description": "Перевод просто так, 23.08.2020 11:59:59, Сумма 200.00 RUB, Банк-он-ЛайнСтатусУспешно Тип операцииПеревод по заявлению клиентаСумма операции200.00 ₽Проведено200.00 ₽Комиссия0.00 ₽Дата обработки23.08.2020Информация о терминалеBank-on-line, Россия, Ekaterinburg, ul. Chapaeva 3aОписаниеПеревод просто так, 23.08.2020 11:59:59, Сумма 200.00 RUB, Банк-он-Лайн",
          "amount": 200.0,
          "commission": 0.0
        },
        {
          "date": "2020-08-23",
          "processingDate": "2020-08-23",
          "description": "Покупка/продажа иностранной валюты от 23/08/2020. Без НДС, 23.08.2020 11:59:59, Сумма 100.08 RUB, Банк-он-ЛайнСтатусУспешно Тип операцииПеревод по заявлению клиентаСумма операции100.08 ₽Проведено100.08 ₽Комиссия0.00 ₽Дата обработки23.08.2020Информация о терминалеBank-on-line, Россия, Ekaterinburg, ul. Chapaeva 3aОписаниеПокупка/продажа иностранной валюты от 23/08/2020. Без НДС, 23.08.2020 11:59:59, Сумма 100.08 RUB, Банк-он-Лайн",
          "amount": 100.08,
          "commission": 0.0
        }
      ]
    }
  ]
}